LONG_DESCRIPTION.rst
MANIFEST.in
setup.cfg
setup.py
XVector.egg-info/PKG-INFO
XVector.egg-info/SOURCES.txt
XVector.egg-info/dependency_links.txt
XVector.egg-info/requires.txt
XVector.egg-info/top_level.txt
xvector/DataSet.py
xvector/XRequest.py
xvector/XVector.py
xvector/__init__.py
xvector/api_config.py
xvector/get.py
xvector/utils/__init__.py
xvector/utils/api_key_util.py