Metadata-Version: 1.0
Name: XVector
Version: 1.0.3
Summary: Package for XVector API access
Home-page: https://gitlab.com/xvectorlabs/pythoncli
Author: XVector Development Team
Author-email: hemant.nadakuditi@xvectorlabs.com
License: UNKNOWN
Keywords: XVECTOR,API,data
Platform: UNKNOWN
